{
  "$schema": "https://json-schema.org/draft/2020-12/schema",
  "title": "Chicken Dad Work",
  "type": "object",
  "required": [
    "title",
    "slug",
    "series",
    "source",
    "status"
  ],
  "properties": {
    "title": {
      "type": "string"
    },
    "slug": {
      "type": "string"
    },
    "series": {
      "type": "string"
    },
    "category": {
      "type": "string"
    },
    "source": {
      "type": "string"
    },
    "status": {
      "type": "string"
    },
    "summary": {
      "type": "string"
    },
    "tags": {
      "type": "array",
      "items": {
        "type": "string"
      }
    },
    "people": {
      "type": "array",
      "items": {
        "type": "string"
      }
    },
    "readingTime": {
      "type": "string"
    },
    "hero": {
      "type": "string"
    },
    "related": {
      "type": "array",
      "items": {
        "type": "string"
      }
    }
  }
}